{
    "facdocs": {
      "factura": [
        {
          "id": "1",
          "number": "001003043567143",
          "code_service": "I0247963",
          "code_princip": "8043",
          "valu_princip": "96.10"
        },
        {
          "id": "2",
          "number": "001003043567143",
          "code_service": "I0247964",
          "code_princip": "8043",
          "valu_princip": "96.10"
        },
        {
          "id": "3",
          "number": "001003043567143",
          "code_service": "I0247965",
          "code_princip": "8043",
          "valu_princip": "96.10"
        },
        {
          "id": "4",
          "number": "001003043567143",
          "code_service": "I0247958",
          "code_princip": "8043",
          "valu_princip": "96.10"
        },
        {
          "id": "5",
          "number": "001003043567143",
          "code_service": "I0247960",
          "code_princip": "8043",
          "valu_princip": "96.10"
        },
        {
          "id": "6",
          "number": "001003043567143",
          "code_service": "I0247961",
          "code_princip": "8043",
          "valu_princip": "96.10"
        },
        {
          "id": "7",
          "number": "001003043567143",
          "code_service": "I0247971",
          "code_princip": "8043",
          "valu_princip": "96.10"
        },
        {
          "id": "8",
          "number": "001003043567143",
          "code_service": "I0248142",
          "code_princip": "8043",
          "valu_princip": "96.10"
        },
        {
          "id": "9",
          "number": "001003043567143",
          "code_service": "I0247970",
          "code_princip": "8043",
          "valu_princip": "96.10"
        },
        {
          "id": "10",
          "number": "001003043567143",
          "code_service": "I0247968",
          "code_princip": "8043",
          "valu_princip": "96.10"
        },
        {
          "id": "11",
          "number": "001003043567143",
          "code_service": "I0247969",
          "code_princip": "8043",
          "valu_princip": "96.10"
        },
        {
          "id": "12",
          "number": "001003043567143",
          "code_service": "RDD01974",
          "code_princip": "8043",
          "valu_princip": "96.10"
        },
        {
          "id": "13",
          "number": "001003043567143",
          "code_service": "RDD02235",
          "code_princip": "8043",
          "valu_princip": "96.10"
        },
        {
          "id": "14",
          "number": "001003043567143",
          "code_service": "RDD02296",
          "code_princip": "8043",
          "valu_princip": "96.10"
        },
        {
          "id": "15",
          "number": "001003043567143",
          "code_service": "RDD01966",
          "code_princip": "8043",
          "valu_princip": "96.10"
        },
        {
          "id": "16",
          "number": "001003043567143",
          "code_service": "RDD01972",
          "code_princip": "8043",
          "valu_princip": "96.10"
        },
        {
          "id": "17",
          "number": "001003043567143",
          "code_service": "RDD01973",
          "code_princip": "8043",
          "valu_princip": "96.10"
        },
        {
          "id": "18",
          "number": "001003043567143",
          "code_service": "I0247955",
          "code_princip": "8043",
          "valu_princip": "96.10"
        },
        {
          "id": "19",
          "number": "001003043567143",
          "code_service": "I0247956",
          "code_princip": "8043",
          "valu_princip": "96.10"
        },
        {
          "id": "20",
          "number": "001003043567143",
          "code_service": "I0247954",
          "code_princip": "8043",
          "valu_princip": "96.10"
        },
        {
          "id": "21",
          "number": "001003043567143",
          "code_service": "I0205929",
          "code_princip": "8043",
          "valu_princip": "96.10"
        },
        {
          "id": "22",
          "number": "001003043567143",
          "code_service": "I0242176",
          "code_princip": "8043",
          "valu_princip": "96.10"
        }
      ]
    }
  }